pytest_typing_runner/__init__.py
pytest_typing_runner/builders.py
pytest_typing_runner/collect.py
pytest_typing_runner/errors.py
pytest_typing_runner/expectations.py
pytest_typing_runner/file_changers.py
pytest_typing_runner/notice_changers.py
pytest_typing_runner/notices.py
pytest_typing_runner/protocols.py
pytest_typing_runner/py.typed
pytest_typing_runner/runners.py
pytest_typing_runner/scenarios.py
pytest_typing_runner/strategies.py
pytest_typing_runner/version.py
pytest_typing_runner/parse/__init__.py
pytest_typing_runner/parse/errors.py
pytest_typing_runner/parse/file_content.py
pytest_typing_runner/parse/mypy_output.py
pytest_typing_runner/parse/protocols.py
pytest_typing_runner-0.6.2.dist-info/METADATA
pytest_typing_runner-0.6.2.dist-info/WHEEL
pytest_typing_runner-0.6.2.dist-info/entry_points.txt
pytest_typing_runner-0.6.2.dist-info/licenses/LICENSE
pytest_typing_runner-0.6.2.dist-info/RECORD
