Metadata-Version: 2.4
Name: pytest-typing-runner
Version: 0.6.2
Summary: Pytest plugin to make it easier to run and check python code against static type checkers
Project-URL: repository, https://github.com/delfick/pytest-typing-runner
Project-URL: changelog, https://pytest-typing-runner.readthedocs.io/en/latest/api/changelog.html
Project-URL: docs, https://pytest-typing-runner.readthedocs.io
Author-email: Stephen Moore <stephen@delfick.com>
License: MIT
License-File: LICENSE
Classifier: Intended Audience :: Developers
Classifier: License :: OSI Approved :: MIT License
Classifier: Operating System :: OS Independent
Classifier: Programming Language :: Python :: 3
Classifier: Programming Language :: Python :: 3 :: Only
Classifier: Programming Language :: Python :: 3.10
Classifier: Programming Language :: Python :: 3.11
Classifier: Programming Language :: Python :: 3.12
Classifier: Typing :: Typed
Requires-Python: >=3.10
